minterpy/__init__.py
minterpy/dds.py
minterpy/gen_points.py
minterpy/global_settings.py
minterpy/interpolation.py
minterpy/py.typed
minterpy/services.py
minterpy/version.py
minterpy/core/__init__.py
minterpy/core/grid.py
minterpy/core/multi_index.py
minterpy/core/tree.py
minterpy/core/ABC/__init__.py
minterpy/core/ABC/multivariate_polynomial_abstract.py
minterpy/core/ABC/operator_abstract.py
minterpy/core/ABC/transformation_abstract.py
minterpy/extras/regression/__init__.py
minterpy/extras/regression/ordinary_regression.py
minterpy/extras/regression/regression_abc.py
minterpy/jit_compiled/__init__.py
minterpy/jit_compiled/canonical.py
minterpy/jit_compiled/common.py
minterpy/jit_compiled/multi_index.py
minterpy/jit_compiled/transformations.py
minterpy/jit_compiled/newton/__init__.py
minterpy/jit_compiled/newton/diff.py
minterpy/jit_compiled/newton/eval.py
minterpy/polynomials/__init__.py
minterpy/polynomials/canonical_polynomial.py
minterpy/polynomials/chebyshev_polynomial.py
minterpy/polynomials/lagrange_polynomial.py
minterpy/polynomials/newton_polynomial.py
minterpy/schemes/__init__.py
minterpy/schemes/matrix_operator.py
minterpy/schemes/barycentric/__init__.py
minterpy/schemes/barycentric/conversion.py
minterpy/schemes/barycentric/operators.py
minterpy/schemes/barycentric/precomp.py
minterpy/schemes/barycentric/transformation_fcts.py
minterpy/transformations/__init__.py
minterpy/transformations/canonical.py
minterpy/transformations/chebyshev.py
minterpy/transformations/identity.py
minterpy/transformations/interface.py
minterpy/transformations/lagrange.py
minterpy/transformations/newton.py
minterpy/transformations/utils.py
minterpy/utils/__init__.py
minterpy/utils/arrays.py
minterpy/utils/multi_index.py
minterpy/utils/quad.py
minterpy/utils/verification.py
minterpy/utils/polynomials/__init__.py
minterpy/utils/polynomials/canonical.py
minterpy/utils/polynomials/chebyshev.py
minterpy/utils/polynomials/interface.py
minterpy/utils/polynomials/lagrange.py
minterpy-0.3.1.dist-info/licenses/LICENSE
minterpy-0.3.1.dist-info/METADATA
minterpy-0.3.1.dist-info/WHEEL
minterpy-0.3.1.dist-info/top_level.txt
minterpy-0.3.1.dist-info/RECORD
