Metadata-Version: 2.4
Name: minterpy
Version: 0.3.1
Summary: Python library for multivariate polynomial interpolation.
Home-page: https://github.com/minterpy-project/minterpy
Author: file: AUTHORS.md
Author-email: u.hernandez@hzdr.de
Maintainer: Minterpy development team
Maintainer-email: u.hernandez@hzdr.de
License: MIT
Project-URL: Bug Tracker, https://github.com/minterpy-project/minterpy/issues
Platform: Any
Classifier: Development Status :: 4 - Beta
Classifier: Intended Audience :: Developers
Classifier: Intended Audience :: Science/Research
Classifier: Intended Audience :: Education
Classifier: License :: OSI Approved :: MIT License
Classifier: Operating System :: OS Independent
Classifier: Programming Language :: Python
Classifier: Programming Language :: Python :: 3
Classifier: Programming Language :: Python :: 3 :: Only
Classifier: Programming Language :: Python :: 3.8
Classifier: Programming Language :: Python :: 3.9
Classifier: Programming Language :: Python :: 3.10
Classifier: Topic :: Scientific/Engineering
Requires-Python: >=3.8
License-File: LICENSE
Requires-Dist: attrs>=20.3.0
Requires-Dist: numba>=0.53.1
Requires-Dist: numpy>=1.13.3
Requires-Dist: scipy>=1.6.3
Provides-Extra: dev
Requires-Dist: black>=24.8.0; extra == "dev"
Requires-Dist: pre-commit>=3.5.0; extra == "dev"
Requires-Dist: pytest>=4.6; extra == "dev"
Requires-Dist: pytest-cov>=2.12.0; extra == "dev"
Provides-Extra: docs
Requires-Dist: Sphinx>=3.0.0; extra == "docs"
Requires-Dist: matplotlib>=3.4.2; extra == "docs"
Requires-Dist: numba>=0.53.1; extra == "docs"
Requires-Dist: numpy>=1.13.3; extra == "docs"
Requires-Dist: pytest>=4.6; extra == "docs"
Requires-Dist: pytest-cov>=2.12.0; extra == "docs"
Requires-Dist: scipy>=1.6.3; extra == "docs"
Requires-Dist: myst-nb>=0.17.2; extra == "docs"
Requires-Dist: nbmake>=1.5.4; extra == "docs"
Requires-Dist: ipykernel>=6.9.1; extra == "docs"
Requires-Dist: ipython-genutils>=0.2.0; extra == "docs"
Requires-Dist: jupyterlab>=4.0.6; extra == "docs"
Requires-Dist: sphinx-copybutton>=0.5.0; extra == "docs"
Requires-Dist: sphinxcontrib.bibtex>=2.4.1; extra == "docs"
Requires-Dist: sphinx-autobuild>=2021.3.14; extra == "docs"
Requires-Dist: pydata-sphinx-theme>=0.7.2; extra == "docs"
Requires-Dist: sphinx-design>=0.5.0; extra == "docs"
Provides-Extra: all
Requires-Dist: minterpy[dev]; extra == "all"
Requires-Dist: minterpy[docs]; extra == "all"
Dynamic: license-file
